test_package_baseball-0.2.0.dist-info/METADATA
test_package_baseball-0.2.0.dist-info/WHEEL
test_package_baseball-0.2.0.dist-info/entry_points.txt
test_package_baseball/__init__.py
test_package_baseball-0.2.0.dist-info/RECORD
